scripts/__init__.py
scripts/deploy_test_container.py
scripts/launch_instance.py
server_managers/__init__.py
server_managers/docker_managers.py
server_managers/ec2_managers.py
server_managers/server_managers.py
tests/__init__.py
tests/functional/__init__.py
tests/functional/test_connections.py
tests/functional/test_firewall_managers.py
tests/functional/test_server_managers.py
tests/integration/__init__.py
tests/unit/__init__.py
tests/unit/test_docker_instances.py
utils/__init__.py
utils/connection_tools.py
utils/constants.py
utils/file_and_directory_tools.py
utils/firewall_managers.py
utils/vpc_managers.py
orionservermanager_pkg_rioatmadja2018-0.1.1592007196.dist-info/METADATA
orionservermanager_pkg_rioatmadja2018-0.1.1592007196.dist-info/WHEEL
orionservermanager_pkg_rioatmadja2018-0.1.1592007196.dist-info/top_level.txt
orionservermanager_pkg_rioatmadja2018-0.1.1592007196.dist-info/zip-safe
orionservermanager_pkg_rioatmadja2018-0.1.1592007196.dist-info/RECORD
