Metadata-Version: 2.1
Name: orionservermanager-pkg-rioatmadja2018
Version: 0.1.1592007196
Summary: Engines to manage remote server.
Home-page: UNKNOWN
Author: Rio Atmadja
Author-email: rioatmadja2018@gmail.com
License: UNKNOWN
Platform: UNKNOWN
Classifier: Programming Language :: Python :: 3
Classifier: Operating System :: OS Independent
Classifier: Intended Audience :: Developers
Requires-Python: >=3.6
Requires-Dist: pandas
Requires-Dist: numpy
Requires-Dist: python-magic
Requires-Dist: boto3
Requires-Dist: astroid (==2.3.3)
Requires-Dist: attrs (==19.3.0)
Requires-Dist: backcall (==0.1.0)
Requires-Dist: bcrypt (==3.1.7)
Requires-Dist: botocore (==1.15.34)
Requires-Dist: cffi (==1.14.0)
Requires-Dist: cryptography (==2.8)
Requires-Dist: decorator (==4.4.2)
Requires-Dist: docutils (==0.15.2)
Requires-Dist: fabric (==2.5.0)
Requires-Dist: importlib-metadata (==1.6.0)
Requires-Dist: invoke (==1.4.1)
Requires-Dist: ipython (==7.13.0)
Requires-Dist: ipython-genutils (==0.2.0)
Requires-Dist: isort (==4.3.21)
Requires-Dist: jedi (==0.16.0)
Requires-Dist: jmespath (==0.9.5)
Requires-Dist: lazy-object-proxy (==1.4.3)
Requires-Dist: mccabe (==0.6.1)
Requires-Dist: more-itertools (==8.2.0)
Requires-Dist: packaging (==20.3)
Requires-Dist: paramiko (==2.7.1)
Requires-Dist: parso (==0.6.2)
Requires-Dist: pexpect (==4.8.0)
Requires-Dist: pickleshare (==0.7.5)
Requires-Dist: pluggy (==0.13.1)
Requires-Dist: prompt-toolkit (==3.0.5)
Requires-Dist: ptyprocess (==0.6.0)
Requires-Dist: py (==1.8.1)
Requires-Dist: pycparser (==2.20)
Requires-Dist: Pygments (==2.6.1)
Requires-Dist: pylint (==2.4.4)
Requires-Dist: PyNaCl (==1.3.0)
Requires-Dist: pyparsing (==2.4.6)
Requires-Dist: pytest (==5.4.1)
Requires-Dist: python-dateutil (==2.8.1)
Requires-Dist: six (==1.14.0)
Requires-Dist: traitlets (==4.3.3)
Requires-Dist: typed-ast (==1.4.1)
Requires-Dist: urllib3 (==1.25.8)
Requires-Dist: wcwidth (==0.1.9)
Requires-Dist: wrapt (==1.11.2)
Requires-Dist: zipp (==3.1.0)
